usfm_tools/__init__.py
usfm_tools/transform.py
usfm_tools/support/__init__.py
usfm_tools/support/abstractRenderer.py
usfm_tools/support/asciiRenderer.py
usfm_tools/support/books.py
usfm_tools/support/contextRenderer.py
usfm_tools/support/csvRenderer.py
usfm_tools/support/htmlRenderer.py
usfm_tools/support/loutRenderer.py
usfm_tools/support/mdRenderer.py
usfm_tools/support/mediawikiPrinter.py
usfm_tools/support/oldhtmlRenderer.py
usfm_tools/support/parseUsfm.py
usfm_tools/support/readerise.py
usfm_tools/support/singlehtmlRenderer.py
usfm_tools/support/usxRenderer.py
usfm_tools-0.0.31.dist-info/LICENSE
usfm_tools-0.0.31.dist-info/METADATA
usfm_tools-0.0.31.dist-info/WHEEL
usfm_tools-0.0.31.dist-info/top_level.txt
usfm_tools-0.0.31.dist-info/RECORD
