Metadata-Version: 2.1
Name: usfm-tools
Version: 0.0.31
Summary: A framework for transforming .usfm files into specified targets
Home-page: https://github.com/unfoldingWord-dev/USFM-Tools
Author: unfoldingWord
Author-email: info@unfoldingWord.org
License: MIT
Keywords: unfoldingWord usfm tools
Platform: UNKNOWN
Requires-Dist: future (==0.18.2)
Requires-Dist: pyparsing (==2.4.5)
